{"date":"2024-12-28","region":"US-MD-033","species":["ambduc","amecro","amegfi","amekes","amerob","baleag","belkin1","blkvul","blujay","buffle","cangoo","carchi","carwre","comloo","commer","coohaw","daejun","doccor","dowwoo","easblu","easpho","eursta","fiespa","fiscro","gadwal","grbher3","greegr","grhowl","haiwoo","herthr","hoomer","houfin","houspa","killde","leasan","lessca","mallar3","moudov","norcar","norfli","normoc","pibgre","pilwoo","rebwoo","redhea","rehwoo","reshaw","rethaw","rewbla","ribgul","rinduc","rocpig","ruckin","rudduc","sonspa","sora","swaspa","tuftit","turvul","virrai","whbnut","whtspa","winwre3","wooduc","yebsap"],"n":65,"fetched_at":"2026-07-02T22:29:46+00:00"}
