{"date":"2025-02-01","region":"US-MD-033","species":["ambduc","amecro","amegfi","amepip","amerob","amewig","amhgul1","baleag","belkin1","blkvul","blujay","bnhcow","brdowl","brncre","brnthr","buffle","cacgoo1","cangoo","canvas","carchi","carwre","cedwax","comgra","commer","coohaw","daejun","doccor","dowwoo","easblu","easpho","eastow","eursta","fiespa","fiscro","gadwal","gnwtea","gockin","grbher3","grycat","haiwoo","herthr","hoomer","houfin","houspa","killde","lbbgul","lessca","mallar3","merlin","moudov","norcar","norfli","norhar2","normoc","norpin","norsho","pibgre","pilwoo","purfin","rebwoo","redhea","reshaw","rethaw","rewbla","ribgul","rinduc","rocpig","ruckin","rudduc","savspa","sonspa","swaspa","tuftit","turvul","whbnut","whtspa","winwre3","y00475","yebsap","yerwar"],"n":80,"fetched_at":"2026-07-02T22:31:32+00:00"}
