{"date":"2025-03-28","region":"US-MD-033","species":["amecro","amegfi","amekes","amerob","amhgul1","baleag","barswa","belkin1","blkvul","blujay","bnhcow","bongul","brdowl","brncre","brnthr","buffle","buggna","buwtea","cangoo","carchi","carwre","chispa","comgra","comrav","coohaw","daejun","doccor","dowwoo","easblu","easmea","easpho","eastow","eursta","fiespa","fiscro","gnwtea","gockin","grbher3","greyel","haiwoo","herthr","hoomer","houfin","houspa","killde","lessca","mallar3","moudov","norcar","norfli","norhar2","normoc","nrwswa","osprey","palwar","perfal","pibgre","pilwoo","pinwar","rebwoo","rehwoo","reshaw","rewbla","ribgul","rinduc","rocpig","ruckin","rudduc","rusbla","savspa","sonspa","swaspa","treswa","tuftit","turvul","whbnut","whtspa","wilsni1","winwre3","wooduc","y00475","ycnher","yerwar"],"n":83,"fetched_at":"2026-07-02T22:34:18+00:00"}
