{"date":"2025-11-28","region":"US-MD-033","species":["ambduc","amecro","amegfi","amepip","amerob","amhgul1","amtspa","baleag","belkin1","blkvul","blujay","brncre","buffle","cangoo","carchi","carwre","cedwax","chispa","coohaw","daejun","doccor","dowwoo","easblu","eastow","eursta","fiespa","fiscro","foxspa","gadwal","gnwtea","gockin","grbher3","haiwoo","hoomer","houfin","houspa","mallar3","moudov","norcar","norfli","normoc","norpar","norsho","pibgre","pilwoo","purfin","rebwoo","rehwoo","reshaw","rethaw","retloo","rewbla","ribgul","rinduc","ruckin","rudduc","savspa","shshaw","sonspa","swaspa","tuftit","tunswa","turvul","whbnut","whtspa","winwre3","wooduc","y00475","yebsap","yerwar"],"n":70,"fetched_at":"2026-07-02T23:24:55+00:00"}
