{"date":"2025-10-05","region":"US-MD-033","species":["ambduc","amecro","amegfi","amekes","amered","amerob","amhgul1","baleag","bawwar","belkin1","blkvul","blujay","bnhcow","boboli","brdowl","brncre","brnthr","buhvir","buwtea","camwar","cangoo","carchi","carwre","cedwax","chispa","chiswi","comgra","commer","comrav","comyel","coohaw","dickci","doccor","dowwoo","easblu","easmea","easpho","eastow","eawpew","eursta","fiscro","gbbgul","gnwtea","gockin","grbher3","greegr","greyel","grnher","grycat","haiwoo","houfin","houspa","houwre","indbun","killde","laugul","leafly","magwar","mallar3","marwre","moudov","norcar","norfli","norhar2","normoc","norpar","norwat","palwar","pecsan","pibgre","pilwoo","pinwar","rebnut","rebwoo","reevir1","rehwoo","reshaw","rethaw","rewbla","ribgul","rocpig","rthhum","ruckin","scatan","solsan","sonspa","sora","swaspa","swathr","tuftit","turvul","virrai","whbnut","whevir","whtspa","wilsni1","wooduc","yebcuc","yebsap","yerwar"],"n":100,"fetched_at":"2026-07-02T23:11:57+00:00"}
