{"date":"2025-06-28","region":"US-MD-033","species":["acafly","amecro","amegfi","amerob","baleag","balori","banswa","barswa","belkin1","blkvul","blugrb1","blujay","bnhcow","brdowl","brnthr","buggna","cangoo","carchi","carwre","cedwax","chispa","chiswi","comgra","comrav","comyel","doccor","dowwoo","easblu","easkin","easpho","eastow","eawpew","eawvir1","eursta","fiespa","fiscro","graspa","grbher3","grcfly","grnher","grycat","haiwoo","houfin","houspa","houwre","indbun","killde","leabit","mallar3","moudov","norcar","norfli","normoc","norpar","nrwswa","orcori","osprey","ovenbi1","pilwoo","pinwar","prawar","prowar","purmar","rebwoo","reevir1","reshaw","rethaw","rewbla","rocpig","rthhum","scatan","sonspa","sumtan","treswa","tuftit","turvul","virrai","whbnut","whevir","wilfly","wooduc","woothr","ycnher","yebcha","yebcuc","yetvir"],"n":86,"fetched_at":"2026-07-02T22:48:11+00:00"}
