{"date":"2026-02-22","region":"US-MD-033","species":["ambduc","amecro","amegfi","amerob","amhgul1","amtspa","baleag","belkin1","blujay","bnhcow","brdowl","brnthr","buffle","cangoo","canvas","carchi","carwre","cedwax","comgol","comgra","commer","comrav","daejun","doccor","dowwoo","easblu","eastow","eursta","fiespa","fiscro","foxspa","gadwal","gockin","grbher3","gresca","grhowl","haiwoo","herthr","hoomer","houfin","houspa","lessca","mallar3","moudov","norcar","norfli","norhar2","normoc","norsho","orcwar","pibgre","pilwoo","pinwar","purfin","rebmer","rebnut","rebwoo","redhea","reshaw","rethaw","rewbla","ribgul","rinduc","rolhaw","ruckin","rudduc","savspa","sonspa","swaspa","tuftit","tunswa","whbnut","whtspa","wooduc","y00475","ycnher","yebsap"],"n":77,"fetched_at":"2026-07-02T23:45:34+00:00"}
