{"date":"2026-07-04","region":"US-MD-033","species":["acafly","amecro","amegfi","amekes","amerob","barswa","belkin1","blugrb1","blujay","bnhcow","brdowl","brnthr","buggna","carchi","carwre","chispa","chiswi","comgra","comyel","doccor","dowwoo","easblu","easkin","easpho","eawpew","eawvir1","eursta","fiscro","grbher3","grcfly","grnher","grycat","haiwoo","houfin","houspa","houwre","indbun","killde","louwat","mallar3","moudov","norcar","norfli","normoc","norpar","nrwswa","orcori","osprey","ovenbi1","pilwoo","prowar","purmar","rebwoo","reevir1","reshaw","rewbla","rocpig","rthhum","scatan","sonspa","treswa","tuftit","turvul","whbnut","whevir","wooduc","woothr","yebcuc"],"n":68,"fetched_at":"2026-07-05T11:24:31+00:00"}
