{"date":"2026-04-17","region":"US-MD-033","species":["amecro","amegfi","amekes","amered","amerob","baleag","banswa","barswa","bawwar","belkin1","blkvul","blugrb1","blujay","bnhcow","brdowl","brnthr","brwhaw","buggna","buhvir","cangoo","carchi","carwre","caster1","cedwax","chispa","chiswi","comgra","comloo","comrav","comyel","coohaw","daejun","doccor","dowwoo","easblu","easkin","easmea","easpho","eastow","eawvir1","eursta","fiespa","fiscro","gloibi","gnwtea","graspa","grbher3","greyel","grnher","grycat","haiwoo","herthr","houfin","houspa","houwre","killde","laugul","louwat","mallar3","moudov","norcar","norfli","normoc","norpar","norwat","nrwswa","orcori","osprey","ovenbi1","palwar","pibgre","pilwoo","pinwar","purfin","rebnut","rebwoo","reevir1","rehwoo","reshaw","rethaw","rewbla","ribgul","rocpig","rthhum","ruckin","rusbla","savspa","sonspa","sposan","swaspa","treswa","truswa","tuftit","turvul","vesspa","whbnut","whevir","whtspa","wilsni1","wiltur","wooduc","woothr","ycnher","yelwar1","yerwar","yetvir","yetwar"],"n":107,"fetched_at":"2026-07-02T23:58:31+00:00"}
