{"date":"2024-09-21","region":"US-DC","species":["acafly","ambduc","amecro","amegfi","amekes","amered","amerob","babwar","baleag","balori","bawwar","belkin1","bkbwar","blkvul","blujay","bnhcow","boboli","brdowl","brnthr","btbwar","btnwar","buhvir","buwtea","buwwar","camwar","cangoo","carchi","carwre","caster1","chispa","chiswi","chswar","comgra","comrav","comyel","coohaw","doccor","dowwoo","easblu","easpho","eastow","eawpew","eursta","fiespa","fiscro","gbbgul","grbher3","grcfly","greegr","grnher","grycat","haiwoo","houfin","houspa","houwre","indbun","killde","laugul","leafly","magwar","mallar3","merlin","moudov","naswar","norcar","norfli","normoc","norpar","norsho","norwat","osprey","ovenbi1","palwar","perfal","phivir","pilwoo","rebwoo","reevir1","rehwoo","reshaw","rethaw","rewbla","ribgul","robgro","rocpig","rthhum","ruckin","scatan","shshaw","snoegr","sonspa","sumtan","swathr","tenwar","tuftit","turvul","veery","whbnut","whtspa","wooduc","woothr","yebcuc","yebsap"],"n":103,"fetched_at":"2026-07-02T22:24:51+00:00"}
