{"date":"2025-02-28","region":"US-DC","species":["ambduc","amecro","amegfi","amerob","amewoo","amhgul1","baleag","bcnher","belkin1","blkvul","blujay","bnhcow","brdowl","brncre","brnthr","buffle","cangoo","canvas","carchi","carwre","chispa","comgra","commer","comrav","coohaw","daejun","doccor","dowwoo","easblu","easpho","eastow","eursta","fiespa","fiscro","foxspa","gbbgul","gockin","grbher3","gresca","grycat","haiwoo","herthr","hoomer","horgre","houfin","houspa","killde","lessca","mallar3","moudov","norcar","norfli","normoc","norsho","orcwar","perfal","pibgre","pilwoo","purfin","rebwoo","reshaw","rethaw","rewbla","ribgul","rinduc","rocpig","ruckin","rusbla","shshaw","sonspa","swaspa","treswa","tuftit","tunswa","turvul","whbnut","whtspa","wilsni1","wiltur","winwre3","wooduc","yebsap","yerwar"],"n":83,"fetched_at":"2026-07-02T22:32:52+00:00"}
