{"date":"2025-08-23","region":"US-DC","species":["acafly","amecro","amegfi","amered","amerob","amhgul1","baleag","balori","barswa","bawwar","belkin1","blkvul","blugrb1","blujay","bnhcow","brnthr","btnwar","buggna","cangoo","carchi","carwre","cedwax","chispa","chiswi","chswar","comgra","comrav","comyel","coohaw","doccor","dowwoo","easblu","easkin","easpho","eawpew","eawvir1","eursta","fiscro","forter","grbher3","grcfly","greegr","grnher","grycat","haiwoo","houfin","houspa","houwre","indbun","laugul","mallar3","moudov","norcar","norfli","normoc","norpar","norwat","olsfly","osprey","pilwoo","rebwoo","reevir1","reshaw","rethaw","rewbla","ribgul","rocpig","rthhum","scatan","sonspa","tuftit","turvul","whbnut","wooduc","woothr","yebcuc"],"n":76,"fetched_at":"2026-07-02T23:01:33+00:00"}
